main/__init__.py
main/experiment.py
main/ml.py
si/__init__.py
si/cell.py
si/defect.py
si/lts.py
utils/__init__.py
utils/functions.py
utils/logger.py
utils/matplotlibstyle.py
utils/no_std_streams.py
DPML-1.0.3.dist-info/LICENSE
DPML-1.0.3.dist-info/METADATA
DPML-1.0.3.dist-info/WHEEL
DPML-1.0.3.dist-info/top_level.txt
DPML-1.0.3.dist-info/RECORD
