Metadata-Version: 2.1
Name: DPML
Version: 1.0.3
Summary: Python project for the extraction of defect parameters from lifetime measurements
Home-page: https://github.com/WhyBeU/DPML
Author: Yoann Buratti
License: UNKNOWN
Project-URL: Paper, https://www.nature.com/articles/s41524-020-00410-7
Project-URL: Support, https://github.com/MK8J/semiconductor
Project-URL: Source, https://github.com/WhyBeU/DPML/
Keywords: ML,defects,semiconductor
Platform: UNKNOWN
Classifier: Development Status :: 3 - Alpha
Classifier: Intended Audience :: End Users/Desktop
Classifier: Topic :: Software Development :: Build Tools
Classifier: License :: OSI Approved :: GNU General Public License v3 or later (GPLv3+)
Classifier: Programming Language :: Python :: 3
Classifier: Programming Language :: Python :: 3.6
Classifier: Programming Language :: Python :: 3.7
Classifier: Programming Language :: Python :: 3.8
Classifier: Programming Language :: Python :: 3.9
Classifier: Programming Language :: Python :: 3 :: Only
Requires-Python: >=3.6, <4
Requires-Dist: scikit-learn
Requires-Dist: numpy
Requires-Dist: pandas
Requires-Dist: scipy
Requires-Dist: matplotlib
Requires-Dist: ruamel-yaml
